setup.py
digExtractor/__init__.py
digExtractor/extractor.py
digExtractor/extractor_processor.py
digExtractor/extractor_processor_chain.py
digExtractor.egg-info/PKG-INFO
digExtractor.egg-info/SOURCES.txt
digExtractor.egg-info/dependency_links.txt
digExtractor.egg-info/requires.txt
digExtractor.egg-info/top_level.txt
test/test_extractor.py