Metadata-Version: 1.1
Name: digExtractor
Version: 0.3.8
Summary: digExtractor
Home-page: https://github.com/usc-isi-i2/dig-extractor
Author: Jason Slepicka
Author-email: jasonslepicka@gmail.com
License: UNKNOWN
Download-URL: https://github.com/usc-isi-i2/dig-extractor
Platform: UNKNOWN
